kapso/__init__.py
kapso/__main__.py
kapso/__version__.py
kapso/builder/__init__.py
kapso/builder/agent/__init__.py
kapso/builder/agent/agent.py
kapso/builder/agent/constants.py
kapso/builder/ai/__init__.py
kapso/builder/ai/field.py
kapso/builder/compilation/__init__.py
kapso/builder/compilation/flow_compiler.py
kapso/builder/edges/__init__.py
kapso/builder/edges/edge.py
kapso/builder/flows/__init__.py
kapso/builder/flows/flow.py
kapso/builder/flows/edges/__init__.py
kapso/builder/flows/edges/edge.py
kapso/builder/flows/nodes/__init__.py
kapso/builder/flows/nodes/agent.py
kapso/builder/flows/nodes/base.py
kapso/builder/flows/nodes/decide.py
kapso/builder/flows/nodes/function.py
kapso/builder/flows/nodes/handoff.py
kapso/builder/flows/nodes/send_interactive.py
kapso/builder/flows/nodes/send_template.py
kapso/builder/flows/nodes/send_text.py
kapso/builder/flows/nodes/start.py
kapso/builder/flows/nodes/wait_for_response.py
kapso/builder/messaging/__init__.py
kapso/builder/nodes/__init__.py
kapso/builder/nodes/base.py
kapso/builder/nodes/factory.py
kapso/builder/nodes/subagent/__init__.py
kapso/builder/nodes/subagent/node.py
kapso/builder/nodes/subagent/tools/__init__.py
kapso/builder/nodes/subagent/tools/base.py
kapso/builder/nodes/subagent/tools/knowledge_base.py
kapso/builder/nodes/subagent/tools/mcp_server.py
kapso/builder/nodes/subagent/tools/webhook.py
kapso/builder/nodes/subagent/tools/whatsapp.py
kapso/builder/serialization/__init__.py
kapso/builder/serialization/flow_yaml.py
kapso/builder/serialization/yaml.py
kapso/builder/tools/__init__.py
kapso/cli/__init__.py
kapso/cli/main.py
kapso/cli/commands/__init__.py
kapso/cli/commands/agent.py
kapso/cli/commands/compile.py
kapso/cli/commands/deploy.py
kapso/cli/commands/flow.py
kapso/cli/commands/functions.py
kapso/cli/commands/init.py
kapso/cli/commands/login.py
kapso/cli/commands/logout.py
kapso/cli/commands/pull.py
kapso/cli/commands/push.py
kapso/cli/commands/run.py
kapso/cli/commands/test.py
kapso-0.4.0.dist-info/METADATA
kapso-0.4.0.dist-info/WHEEL
kapso-0.4.0.dist-info/entry_points.txt
kapso-0.4.0.dist-info/top_level.txt
kapso-0.4.0.dist-info/RECORD
