Metadata-Version: 2.4
Name: kapso
Version: 0.4.0
Summary: WhatsApp AI Agents
Home-page: https://kapso.ai
Author: Kapso AI
Author-email: dev@kap.so
Project-URL: Documentation, https://docs.kapso.ai
Project-URL: Support, https://docs.kapso.ai
Classifier: Development Status :: 4 - Beta
Classifier: Intended Audience :: Developers
Classifier: License :: Other/Proprietary License
Classifier: Programming Language :: Python :: 3
Classifier: Programming Language :: Python :: 3.10
Classifier: Programming Language :: Python :: 3.11
Classifier: Programming Language :: Python :: 3.12
Classifier: Operating System :: OS Independent
Classifier: Topic :: Software Development :: Libraries :: Python Modules
Classifier: Topic :: Communications :: Chat
Classifier: Topic :: Scientific/Engineering :: Artificial Intelligence
Requires-Python: >=3.10
Requires-Dist: typer>=0.9.0
Requires-Dist: rich>=13.0.0
Requires-Dist: pyyaml>=6.0
Requires-Dist: httpx
Requires-Dist: pydantic>=2.0.0
Requires-Dist: pydantic-settings
Requires-Dist: python-dotenv
Requires-Dist: click==8.1.7
Requires-Dist: keyring
Requires-Dist: inquirer
Requires-Dist: sentry-sdk>=2.0.0
Requires-Dist: python-dateutil
Dynamic: author
Dynamic: author-email
Dynamic: classifier
Dynamic: description
Dynamic: description-content-type
Dynamic: home-page
Dynamic: project-url
Dynamic: requires-dist
Dynamic: requires-python
Dynamic: summary
